artifician/__init__.py
artifician/dataset.py
artifician/feature_definition.py
artifician/extractors/__init__.py
artifician/extractors/html_extractors.py
artifician/processors/__init__.py
artifician/processors/chain.py
artifician/processors/mapper.py
artifician/processors/normalizer.py
artifician/processors/processor.py
artifician/processors/text/__init__.py
artifician/processors/text/stemlemtizer.py
artifician/processors/text/stop_word_remover.py
artifician/processors/text/text_cleaner.py
artifician/processors/text/tokenizer.py
tests/__init__.py
tests/functional/__init__.py
tests/functional/test_mapper.py
tests/functional/test_normalizer.py
tests/functional/test_strategy_selector.py
tests/integration/__init__.py
tests/integration/test_feature_definition.py
tests/integration/test_html_extractors.py
tests/integration/test_processor_chain_manager.py
tests/unit/__init__.py
tests/unit/test_html_extractors.py
tests/unit/test_processor_chain_manager.py
tests/unit/text_processors/__init__.py
tests/unit/text_processors/test_stemlemitizer.py
tests/unit/text_processors/test_stop_word_remover.py
tests/unit/text_processors/test_text_cleaner.py
tests/unit/text_processors/test_tokenizer.py
artifician-0.6.4.dist-info/LICENSE
artifician-0.6.4.dist-info/METADATA
artifician-0.6.4.dist-info/WHEEL
artifician-0.6.4.dist-info/top_level.txt
artifician-0.6.4.dist-info/RECORD
