Metadata-Version: 2.1
Name: artifician
Version: 0.6.4
Summary: Artifician is an event driven framework developed to simplify the process of preparation of the dataset for Artificial Intelligence models.
Home-page: https://github.com/Plato-solutions/artifician
Author: Abhijeet Gandhi
Author-email: abhijeet@platoanalytics.com
License: Apache-2.0
Project-URL: Documentation, https://plato-solutions.gitbook.io/artifician/
Project-URL: Source, https://github.com/Plato-solutions/artifician
Keywords: python artifician
Classifier: Development Status :: 4 - Beta
Requires-Python: >=3.6
License-File: LICENSE
Requires-Dist: pandas
Requires-Dist: rx >=3.2.0
Requires-Dist: beautifulsoup4
Requires-Dist: spacy
Requires-Dist: nltk
